LICENSE
MANIFEST.in
README
setup.py
django_masquerade.egg-info/PKG-INFO
django_masquerade.egg-info/SOURCES.txt
django_masquerade.egg-info/dependency_links.txt
django_masquerade.egg-info/top_level.txt
doc_src/Makefile
doc_src/conf.py
doc_src/index.rst
doc_src/make.bat
doc_src/_build/doctrees/environment.pickle
doc_src/_build/doctrees/index.doctree
doc_src/_static/breadcrumb_background.png
doc_src/_static/default.css
doc_src/_static/documentation.png
doc_src/_static/header_sm_mid.png
doc_src/_static/scrn1.png
doc_src/_static/scrn2.png
doc_src/_static/searchfield_leftcap.png
doc_src/_static/searchfield_repeat.png
doc_src/_static/searchfield_rightcap.png
doc_src/_static/title_background.png
doc_src/_static/toc.js
doc_src/_static/triangle_closed.png
doc_src/_static/triangle_left.png
doc_src/_static/triangle_open.png
doc_src/_templates/layout.html
docs/.buildinfo
docs/genindex.html
docs/index.html
docs/objects.inv
docs/search.html
docs/searchindex.js
docs/_sources/index.txt
docs/_static/basic.css
docs/_static/breadcrumb_background.png
docs/_static/default.css
docs/_static/doctools.js
docs/_static/documentation.png
docs/_static/file.png
docs/_static/header_sm_mid.png
docs/_static/jquery.js
docs/_static/minus.png
docs/_static/plus.png
docs/_static/pygments.css
docs/_static/scrn1.png
docs/_static/scrn2.png
docs/_static/searchfield_leftcap.png
docs/_static/searchfield_repeat.png
docs/_static/searchfield_rightcap.png
docs/_static/searchtools.js
docs/_static/sidebar.js
docs/_static/title_background.png
docs/_static/toc.js
docs/_static/triangle_closed.png
docs/_static/triangle_left.png
docs/_static/triangle_open.png
docs/_static/underscore.js
masquerade/__init__.py
masquerade/forms.py
masquerade/middleware.py
masquerade/models.py
masquerade/tests.py
masquerade/urls.py
masquerade/views.py
masquerade/templates/masquerade/mask_form.html
masquerade/templatetags/__init__.py
masquerade/templatetags/masquerade.py