Metadata-Version: 1.0
Name: django-masquerade
Version: 0.1
Summary: django-masquerade
Home-page: https://bitbucket.org/technivore/django-masquerade
Author: Matthew Rich
Author-email: matthew@technivore.org
License: UNKNOWN
Platform: UNKNOWN
Classifier: License :: OSI Approved :: Apache Software License
Classifier: Framework :: Django
